LICENSE
MANIFEST.in
README.rst
setup.py
Flask_HTAuth.egg-info/PKG-INFO
Flask_HTAuth.egg-info/SOURCES.txt
Flask_HTAuth.egg-info/dependency_links.txt
Flask_HTAuth.egg-info/not-zip-safe
Flask_HTAuth.egg-info/requires.txt
Flask_HTAuth.egg-info/top_level.txt
flask_htauth/__init__.py
flask_htauth/extension.py
flask_htauth/htpasswd.py