Metadata-Version: 1.0
Name: Flask-HTAuth
Version: 0.1.2
Summary: Easy to integrate basic HTTP authentication for Flask apps
Home-page: http://tomekwojcik.github.com/flask-htauth/
Author: Tomasz Wójcik
Author-email: tomek@bthlabs.pl
License: https://github.com/tomekwojcik/flask-htauth/blob/master/LICENSE
Download-URL: https://github.com/tomekwojcik/flask-htauth/tarball/v0.1.2
Platform: any
Classifier: Development Status :: 4 - Beta
Classifier: Environment :: Web Environment
Classifier: Intended Audience :: Developers
Classifier: License :: OSI Approved :: MIT License
Classifier: Operating System :: OS Independent
Classifier: Programming Language :: Python
Classifier: Topic :: Internet :: WWW/HTTP :: Dynamic Content
Classifier: Topic :: Software Development :: Libraries :: Python Modules
